milesight_gateway_api/__init__.py
milesight_gateway_api/milesight_gateway_client.py
Milesight_Gateway_API-0.0.1.dist-info/LICENSE
Milesight_Gateway_API-0.0.1.dist-info/METADATA
Milesight_Gateway_API-0.0.1.dist-info/WHEEL
Milesight_Gateway_API-0.0.1.dist-info/top_level.txt
Milesight_Gateway_API-0.0.1.dist-info/RECORD
